hyperstream/__init__.py
hyperstream/components.py
hyperstream/hstag.py
hyperstream/hyperstream.py
hyperstream/runner.py
html_stream-0.0.1.dist-info/METADATA
html_stream-0.0.1.dist-info/WHEEL
html_stream-0.0.1.dist-info/top_level.txt
html_stream-0.0.1.dist-info/RECORD
