Metadata-Version: 2.1
Name: html-stream
Version: 0.0.1
Summary: Create python webapps with ease
Home-page: http://packages.python.org/hyperstream
Author: Conrad Bezuidenhout
Author-email: conradbez1@gmail.com
License: BSD
Keywords: streamlit htmx fastapi
Classifier: Development Status :: 3 - Alpha
Classifier: Topic :: Utilities
Classifier: License :: OSI Approved :: BSD License
